ahttp_client/__init__.py
ahttp_client/_types.py
ahttp_client/body.py
ahttp_client/body_json.py
ahttp_client/component.py
ahttp_client/form.py
ahttp_client/header.py
ahttp_client/path.py
ahttp_client/query.py
ahttp_client/request.py
ahttp_client/session.py
ahttp_client/utils.py
ahttp_client/extension/__init__.py
ahttp_client/extension/multiple_hook.py
ahttp_client/extension/pydantic.py
ahttp_client-1.0.3.dist-info/LICENSE
ahttp_client-1.0.3.dist-info/METADATA
ahttp_client-1.0.3.dist-info/WHEEL
ahttp_client-1.0.3.dist-info/top_level.txt
ahttp_client-1.0.3.dist-info/RECORD
