Metadata-Version: 2.2
Name: ahttp_client
Version: 1.0.3
Summary: A framework for easy asynchronous HTTP request calling with decorations
Home-page: https://github.com/gunyu1019/ahttp-client
Author: gunyu1019
Author-email: gunyu1019@yhs.kr
License: MIT
Classifier: Development Status :: 5 - Production/Stable
Classifier: License :: OSI Approved :: MIT License
Classifier: Intended Audience :: Developers
Classifier: Natural Language :: Korean
Classifier: Natural Language :: English
Classifier: Programming Language :: Python
Classifier: Programming Language :: Python :: 3
Classifier: Programming Language :: Python :: 3.10
Classifier: Programming Language :: Python :: 3.11
Classifier: Programming Language :: Python :: 3.12
Classifier: Topic :: Internet
Classifier: Topic :: Software Development :: Libraries
Classifier: Topic :: Software Development :: Libraries :: Python Modules
Classifier: Topic :: Utilities
Requires-Python: >=3.10
License-File: LICENSE
Requires-Dist: aiohappyeyeballs==2.4.6
Requires-Dist: aiohttp==3.11.12
Requires-Dist: aiosignal==1.3.2
Requires-Dist: async-timeout==5.0.1
Requires-Dist: attrs==25.1.0
Requires-Dist: charset-normalizer==3.4.1
Requires-Dist: frozenlist==1.5.0
Requires-Dist: idna==3.10
Requires-Dist: multidict==6.1.0
Requires-Dist: propcache==0.3.0
Requires-Dist: yarl==1.18.3
Provides-Extra: test
Requires-Dist: pytest; extra == "test"
Requires-Dist: pytest-cov; extra == "test"
Provides-Extra: lint
Requires-Dist: pycodestyle; extra == "lint"
Requires-Dist: black; extra == "lint"
Provides-Extra: docs
Requires-Dist: Sphinx; extra == "docs"
Requires-Dist: sphinxawesome-theme; extra == "docs"
Requires-Dist: sphinx-intl; extra == "docs"
Dynamic: author
Dynamic: author-email
Dynamic: classifier
Dynamic: description
Dynamic: description-content-type
Dynamic: home-page
Dynamic: license
Dynamic: provides-extra
Dynamic: requires-dist
Dynamic: requires-python
Dynamic: summary
